Kinetics_LBMC/HomogeneousMatrix.py
Kinetics_LBMC/Joint.py
Kinetics_LBMC/KinematicChain.py
Kinetics_LBMC/Segment.py
Kinetics_LBMC/__init__.py
Kinetics_LBMC/joint_model.py
Kinetics_LBMC/multi_body_optimisation.py
Kinetics_LBMC/utils/__init__.py
Kinetics_LBMC/utils/homogenous2rotation.py
Kinetics_LBMC/utils/inertia_matrix.py
Kinetics_LBMC/utils/norm_vector.py
Kinetics_LBMC/utils/plateforme_extraction.py
Kinetics_LBMC/utils/points_treatment.py
Kinetics_LBMC/utils/r2mobile.py
Kinetics_LBMC/utils/vnop_array.py
demo/__init__.py
demo/extraction_pycgm2.py
demo/pycgme2_inverse_kinematci_demo.py
kinetics_lbmc-0.0.1.dist-info/METADATA
kinetics_lbmc-0.0.1.dist-info/WHEEL
kinetics_lbmc-0.0.1.dist-info/licence.txt
kinetics_lbmc-0.0.1.dist-info/top_level.txt
kinetics_lbmc-0.0.1.dist-info/RECORD
