Metadata-Version: 2.1
Name: kinetics-lbmc
Version: 0.0.1
Summary: A tool box for to calculate kinematics and kinetics based on natural coordinates and homogeneous formulation. 
Home-page: https://github.com/ANaaim/Kinetics_LBMC
Author: Alexandre Naaim
Author-email: alexandre.naaim@univ-lyon1.fr
License: UNKNOWN
Platform: UNKNOWN
Classifier: Programming Language :: Python :: 3
Classifier: Operating System :: OS Independent
Requires-Python: >=3.8
